theforecastingcompany/__init__.py
theforecastingcompany/api.py
theforecastingcompany/errors.py
theforecastingcompany/tfc_client.py
theforecastingcompany/utils.py
theforecastingcompany-0.3.0.dist-info/METADATA
theforecastingcompany-0.3.0.dist-info/WHEEL
theforecastingcompany-0.3.0.dist-info/licenses/LICENSE
theforecastingcompany-0.3.0.dist-info/RECORD
