Metadata-Version: 2.4
Name: theforecastingcompany
Version: 0.3.0
Summary: The official Python library for The Forecasting Company API
Project-URL: homepage, https://theforecastingcompany.com
Project-URL: repository, https://github.com/theforecastingcompany/theforecastingcompany-sdk-python
Project-URL: docs, https://api.retrocast.com/docs
Author-email: The Forecasting Company <support@theforecastingcompany.com>
License-Expression: Apache-2.0
License-File: LICENSE
Keywords: api,artificial-intelligence,data-science,deep-learning,forecasting,foundation-model,machine-learning,prediction,python-sdk,tfc,time-series,time-series-forecasting
Requires-Python: >=3.11
Requires-Dist: httpx>=0.28.1
Requires-Dist: nest-asyncio>=1.6.0
Requires-Dist: pandas>=2.2.3
Requires-Dist: pydantic>=2.11.7
Requires-Dist: tqdm>=4.67.1
